wsrLab_demo
