Metadata-Version: 1.0
Name: wsrLab-demo
Version: 0.5
Summary: 这是一个测试文件，用户PyPi测试！
Home-page: http://www.x.com
Author: wsr
Author-email: 702183233@qq.com
License: UNKNOWN
Platform: UNKNOWN
